pyunited/__init__.py
pyunited/typing.py
pyunited/unit.py
pyunited/unit_system.py
pyunited-0.1.1.dist-info/METADATA
pyunited-0.1.1.dist-info/WHEEL
pyunited-0.1.1.dist-info/RECORD
